poetry_azure_artifacts_plugin/__init__.py
poetry_azure_artifacts_plugin/plugin.py
poetry_azure_artifacts_plugin-0.1.3.dist-info/WHEEL
poetry_azure_artifacts_plugin-0.1.3.dist-info/METADATA
poetry_azure_artifacts_plugin-0.1.3.dist-info/RECORD
