Metadata-Version: 2.3
Name: poetry-azure-artifacts-plugin
Version: 0.1.3
Summary: Poetry plugin to handle Azure Artifacts authentication
Author: Nathan Vaughn
Author-email: Nathan Vaughn <nath@nvaughn.email>
Classifier: Intended Audience :: Developers
Classifier: Topic :: Software Development :: Libraries :: Python Modules
Classifier: Topic :: Text Processing
Classifier: License :: OSI Approved :: MIT License
Classifier: Programming Language :: Python :: 3.9
Classifier: Programming Language :: Python :: 3.10
Classifier: Programming Language :: Python :: 3.11
Classifier: Programming Language :: Python :: 3.12
Classifier: Programming Language :: Python :: 3.13
Requires-Dist: artifacts-keyring>=0.3.6
Requires-Dist: poetry>=1.8.0
Requires-Python: >=3.9
Project-URL: Homepage, https://github.com/NathanVaughn/poetry-azure-artifacts-plugin
Project-URL: Repository, https://github.com/NathanVaughn/poetry-azure-artifacts-plugin.git
Project-URL: Issues, https://github.com/NathanVaughn/poetry-azure-artifacts-plugin/issues
